pykonal/transformations.py
pykonal/constants.c
pykonal/locate.pxd
pykonal/locate.cpython-310-x86_64-linux-gnu.so
pykonal/__init__.py
pykonal/fields.cpython-310-x86_64-linux-gnu.so
pykonal/__version__.py
pykonal/fields.pxd
pykonal/solver.pxd
pykonal/fields.cpp
pykonal/stats.pxd
pykonal/constants.cpython-310-x86_64-linux-gnu.so
pykonal/stats.cpython-310-x86_64-linux-gnu.so
pykonal/locate.cpp
pykonal/solver.cpp
pykonal/heapq.cpython-310-x86_64-linux-gnu.so
pykonal/inventory.py
pykonal/solver.cpython-310-x86_64-linux-gnu.so
pykonal/heapq.cpp
pykonal/heapq.pxd
pykonal/stats.c
pykonal/constants.pxd
pykonal/data/ak135.npz
pykonal/data/mitp2008.npz
pykonal/data/marmousi2/LICENSE
pykonal/data/marmousi2/marmousi2.npz
pykonal/data/marmousi2/README
pykonal/tests/data/test_EikonalSolver_uniform_velocity_cartesian.npz
pykonal-0.3.2b6.dist-info/top_level.txt
pykonal-0.3.2b6.dist-info/METADATA
pykonal-0.3.2b6.dist-info/RECORD
pykonal-0.3.2b6.dist-info/WHEEL
pykonal-0.3.2b6.dist-info/LICENSE
