Metadata-Version: 2.1
Name: pykonal
Version: 0.3.2b6
Summary: Solve the Eikonal equation in 3D Cartesian or spherical coordinates.
Home-page: https://github.com/malcolmw/pykonal
Author: Malcolm C. A. White
Author-email: "Malcolm C. A. White" <malcolmw@mit.edu>
License: GNU GPLv3
Project-URL: Homepage, https://github.com/malcolmw/pykonal
Project-URL: Bug Tracker, https://github.com/malcolmw/pykonal/issues
Classifier: Development Status :: 4 - Beta
Classifier: Intended Audience :: Science/Research
Classifier: License :: OSI Approved :: GNU General Public License v3 (GPLv3)
Classifier: Operating System :: MacOS :: MacOS X
Classifier: Operating System :: POSIX :: Linux
Classifier: Programming Language :: Python
Classifier: Programming Language :: Python :: 3
Classifier: Topic :: Scientific/Engineering :: Physics
Requires-Python: >=3
License-File: LICENSE
Requires-Dist: cython (>=0.29.14)
Requires-Dist: h5py
Requires-Dist: numpy
Requires-Dist: scipy
Provides-Extra: tests
Requires-Dist: nose ; extra == 'tests'
